bytes/__init__.py
bytes/pdf.py
bytes/test.py
sm_snake-0.0.2.dist-info/LICENSE
sm_snake-0.0.2.dist-info/METADATA
sm_snake-0.0.2.dist-info/WHEEL
sm_snake-0.0.2.dist-info/entry_points.txt
sm_snake-0.0.2.dist-info/top_level.txt
sm_snake-0.0.2.dist-info/RECORD
